gentag/__init__.py
gentag/exceptions.py
gentag/tests.py
gentag-2.0.dist-info/DESCRIPTION.rst
gentag-2.0.dist-info/METADATA
gentag-2.0.dist-info/RECORD
gentag-2.0.dist-info/WHEEL
gentag-2.0.dist-info/metadata.json
gentag-2.0.dist-info/top_level.txt
