Metadata-Version: 2.0
Name: gentag
Version: 2.0
Summary: Simple and powerful tagging for Python objects.
Home-page: https://github.com/xolox/python-gentag
Author: Peter Odding
Author-email: peter@peterodding.com
License: UNKNOWN
Platform: UNKNOWN
Classifier: Development Status :: 4 - Beta
Classifier: Intended Audience :: Developers
Classifier: Intended Audience :: Information Technology
Classifier: Intended Audience :: System Administrators
Classifier: License :: OSI Approved :: MIT License
Classifier: Programming Language :: Python
Classifier: Programming Language :: Python :: 2
Classifier: Programming Language :: Python :: 2.6
Classifier: Programming Language :: Python :: 2.7
Classifier: Programming Language :: Python :: 3
Classifier: Programming Language :: Python :: 3.4
Classifier: Programming Language :: Python :: 3.5
Classifier: Programming Language :: Python :: 3.6
Classifier: Programming Language :: Python :: Implementation :: CPython
Classifier: Programming Language :: Python :: Implementation :: PyPy
Classifier: Topic :: Software Development
Classifier: Topic :: Software Development :: Libraries
Classifier: Topic :: Software Development :: Libraries :: Python Modules
Classifier: Topic :: Text Processing
Classifier: Topic :: Text Processing :: Indexing
Requires-Dist: humanfriendly (>=4.8)
Requires-Dist: naturalsort (>=1.5.1)
Requires-Dist: property-manager (>=2.2)
Requires-Dist: six (>=1.11.0)
Requires-Dist: verboselogs (>=1.7)
